Workbook

Sheet Cover
B2: Banking — 5-Year Operating Model
B5: Case study calibration: HSBC Holdings plc
B7: MODEL MAP
B8: Cover — this sheet: map, conventions, disclaimer
B9: Inputs — every driver in one place (blue cells are inputs)
B10: Forecast — 5-year bank P&L, tangible-equity rollforward, ratios
B11: Valuation — justified P/TBV, implied equity value, per-share
B13: CONVENTIONS
B14: Blue font = input you can change
B15: Black font = formula (do not overwrite)
B16: Bold = output / subtotal
B18: METHOD
... B30: not investment advice.

Sheet Inputs
A1: Inputs — drivers
A3: Driver | B3: Value | C3: Unit
A4: Earning assets (Y0) | B4: 2300 | C4: USD bn
A5: Asset growth | B5: 0.03 | C5: %
A6: Net interest margin (NIM) | B6: 0.016 | C6: %
A7: Fee & other income (Y0) | B7: 22 | C7: USD bn
A8: Cost-to-income ratio | B8: 0.48 | C8: %
A9: Cost of risk | B9: 0.002 | C9: %
A10: Tax rate | B10: 0.22 | C10: %
A11: Tangible equity (Y0) | B11: 155 | C11: USD bn
A12: Dividend payout | B12: 0.5 | C12: %
A13: Cost of equity (CoE) | B13: 0.105 | C13: %
A14: Terminal growth | B14: 0.03 | C14: %
A15: Shares outstanding (m) | B15: 17800 | C15: millions

Sheet Forecast
A1: Forecast — USD billion
A3: USD billion | C3: Y1 | D3: Y2 | E3: Y3 | F3: Y4 | G3: Y5
A4: Earning assets (avg) | C4: =Inputs!$B$4*(1+Inputs!$B$5)^1 | D4: =Inputs!$B$4*(1+Inputs!$B$5)^2 | E4: =Inputs!$B$4*(1+Inputs!$B$5)^3 | F4: =Inputs!$B$4*(1+Inputs!$B$5)^4 | G4: =Inputs!$B$4*(1+Inputs!$B$5)^5
A5: Fee & other income | C5: =Inputs!$B$7*(1+Inputs!$B$5)^1 | D5: =Inputs!$B$7*(1+Inputs!$B$5)^2 | E5: =Inputs!$B$7*(1+Inputs!$B$5)^3 | F5: =Inputs!$B$7*(1+Inputs!$B$5)^4 | G5: =Inputs!$B$7*(1+Inputs!$B$5)^5
A6: Net interest income | C6: =C4*Inputs!$B$6 | D6: =D4*Inputs!$B$6 | E6: =E4*Inputs!$B$6 | F6: =F4*Inputs!$B$6 | G6: =G4*Inputs!$B$6
A7: Total revenue | C7: =C6+C5 | D7: =D6+D5 | E7: =E6+E5 | F7: =F6+F5 | G7: =G6+G5
A8: Operating expenses | C8: =C7*Inputs!$B$8 | D8: =D7*Inputs!$B$8 | E8: =E7*Inputs!$B$8 | F8: =F7*Inputs!$B$8 | G8: =G7*Inputs!$B$8
A9: Pre-provision profit | C9: =C7-C8 | D9: =D7-D8 | E9: =E7-E8 | F9: =F7-F8 | G9: =G7-G8
A10: Loan-loss provisions | C10: =C4*Inputs!$B$9 | D10: =D4*Inputs!$B$9 | E10: =E4*Inputs!$B$9 | F10: =F4*Inputs!$B$9 | G10: =G4*Inputs!$B$9
A11: Pre-tax profit | C11: =C9-C10 | D11: =D9-D10 | E11: =E9-E10 | F11: =F9-F10 | G11: =G9-G10
A12: Tax | C12: =IF(C11>0,C11*Inputs!$B$10,0) | D12: =IF(D11>0,D11*Inputs!$B$10,0) | E12: =IF(E11>0,E11*Inputs!$B$10,0) | F12: =IF(F11>0,F11*Inputs!$B$10,0) | G12: =IF(G11>0,G11*Inputs!$B$10,0)
A13: Net income | C13: =C11-C12 | D13: =D11-D12 | E13: =E11-E12 | F13: =F11-F12 | G13: =G11-G12
A14: Tangible equity (opening) | C14: =Inputs!$B$11 | D14: =C15 | E14: =D15 | F14: =E15 | G14: =F15
A15: Tangible equity (closing) | C15: =C14+C13*(1-Inputs!$B$12) | D15: =D14+D13*(1-Inputs!$B$12) | E15: =E14+E13*(1-Inputs!$B$12) | F15: =F14+F13*(1-Inputs!$B$12) | G15: =G14+G13*(1-Inputs!$B$12)
A17: Key ratios
A18: ROTE | C18: =C13/C14 | D18: =D13/D14 | E18: =E13/E14 | F18: =F13/F14 | G18: =G13/G14
A19: Cost-to-income | C19: =Inputs!$B$8 | D19: =Inputs!$B$8 | E19: =Inputs!$B$8 | F19: =Inputs!$B$8 | G19: =Inputs!$B$8
A20: NIM | C20: =Inputs!$B$6 | D20: =Inputs!$B$6 | E20: =Inputs!$B$6 | F20: =Inputs!$B$6 | G20: =Inputs!$B$6
A21: Cost of risk | C21: =Inputs!$B$9 | D21: =Inputs!$B$9 | E21: =Inputs!$B$9 | F21: =Inputs!$B$9 | G21: =Inputs!$B$9

Sheet Valuation
A1: Valuation — Justified P/TBV
A3: Equity-based valuation (not a DCF)
A5: Normalized ROTE (Y1) | B5: =Forecast!C13/Forecast!C14
A6: Cost of equity (CoE) | B6: =Inputs!$B$13
A7: Terminal growth (g) | B7: =Inputs!$B$14
A8: Justified P/TBV | B8: =(B5-B7)/(B6-B7)
A9: Tangible equity Y0 (USD bn) | B9: =Inputs!$B$11
A10: Implied equity value (USD bn) | B10: =B8*B9
A11: Shares outstanding (m) | B11: =Inputs!$B$15
A12: Per-share value (USD) | B12: =B10*1000/B11
A14: Note: a bank has no enterprise value — leverage is the business, so
A15: EV/EBITDA and operating-cash DCFs do not apply. P/TBV is the frame.
