Workbook

Sheet Cover
B2: Retail & Consumer — 5-Year Operating Model
B5: Case study calibration: Costco Wholesale (NASDAQ: COST)
B7: MODEL MAP
B8: Cover — this sheet: map, conventions, disclaimer
B9: Inputs — every driver in one place (blue cells are inputs)
B10: Forecast — 5-year income statement, FCFF build, key ratios
B11: Valuation — DCF, terminal value, EV → equity → per-share
B13: CONVENTIONS
B14: Blue font = input you can change
B15: Black font = formula (do not overwrite)
B16: Bold = output / subtotal
B18: METHOD
... B29: Analytical template only — not investment advice.

Sheet Inputs
A1: Inputs — drivers
A3: Driver | B3: Value | C3: Unit
A4: Revenue (Y0) | B4: 254.5 | C4: USD bn
A5: Revenue growth | B5: 0.07 | C5: %
A6: EBITDA margin | B6: 0.047 | C6: %
A7: D&A / revenue | B7: 0.008 | C7: %
A8: Capex intensity | B8: 0.018 | C8: %
A9: Tax rate | B9: 0.25 | C9: %
A10: WACC | B10: 0.075 | C10: %
A11: Terminal growth | B11: 0.03 | C11: %
A12: Net debt (Y0) | B12: -5 | C12: USD bn
A13: Shares outstanding (m) | B13: 445 | C13: millions
A14: Cost of debt | B14: 0.05 | C14: %
A15: WC % of incremental revenue | B15: 0.02 | C15: %

Sheet Forecast
A1: Forecast — USD billion
A3: USD billion | C3: Y1 | D3: Y2 | E3: Y3 | F3: Y4 | G3: Y5
A4: Revenue | C4: =Inputs!$B$4*(1+Inputs!$B$5) | D4: =C4*(1+Inputs!$B$5) | E4: =D4*(1+Inputs!$B$5) | F4: =E4*(1+Inputs!$B$5) | G4: =F4*(1+Inputs!$B$5)
A5: EBITDA | C5: =C4*Inputs!$B$6 | D5: =D4*Inputs!$B$6 | E5: =E4*Inputs!$B$6 | F5: =F4*Inputs!$B$6 | G5: =G4*Inputs!$B$6
A6: D&A | C6: =C4*Inputs!$B$7 | D6: =D4*Inputs!$B$7 | E6: =E4*Inputs!$B$7 | F6: =F4*Inputs!$B$7 | G6: =G4*Inputs!$B$7
A7: EBIT | C7: =C5-C6 | D7: =D5-D6 | E7: =E5-E6 | F7: =F5-F6 | G7: =G5-G6
A8: Interest | C8: =Inputs!$B$12*Inputs!$B$14 | D8: =Inputs!$B$12*Inputs!$B$14 | E8: =Inputs!$B$12*Inputs!$B$14 | F8: =Inputs!$B$12*Inputs!$B$14 | G8: =Inputs!$B$12*Inputs!$B$14
A9: Pre-tax profit | C9: =C7-C8 | D9: =D7-D8 | E9: =E7-E8 | F9: =F7-F8 | G9: =G7-G8
A10: Tax | C10: =IF(C9>0,C9*Inputs!$B$9,0) | D10: =IF(D9>0,D9*Inputs!$B$9,0) | E10: =IF(E9>0,E9*Inputs!$B$9,0) | F10: =IF(F9>0,F9*Inputs!$B$9,0) | G10: =IF(G9>0,G9*Inputs!$B$9,0)
A11: Net income | C11: =C9-C10 | D11: =D9-D10 | E11: =E9-E10 | F11: =F9-F10 | G11: =G9-G10
A12: Capex | C12: =C4*Inputs!$B$8 | D12: =D4*Inputs!$B$8 | E12: =E4*Inputs!$B$8 | F12: =F4*Inputs!$B$8 | G12: =G4*Inputs!$B$8
A13: ΔWorking capital | C13: =(C4-Inputs!$B$4)*Inputs!$B$15 | D13: =(D4-C4)*Inputs!$B$15 | E13: =(E4-D4)*Inputs!$B$15 | F13: =(F4-E4)*Inputs!$B$15 | G13: =(G4-F4)*Inputs!$B$15
A14: NOPAT | C14: =C7*(1-Inputs!$B$9) | D14: =D7*(1-Inputs!$B$9) | E14: =E7*(1-Inputs!$B$9) | F14: =F7*(1-Inputs!$B$9) | G14: =G7*(1-Inputs!$B$9)
A15: FCFF | C15: =C14+C6-C12-C13 | D15: =D14+D6-D12-D13 | E15: =E14+E6-E12-E13 | F15: =F14+F6-F12-F13 | G15: =G14+G6-G12-G13
A17: Key ratios
A18: EBITDA margin | C18: =C5/C4 | D18: =D5/D4 | E18: =E5/E4 | F18: =F5/F4 | G18: =G5/G4
A19: FCF / revenue | C19: =C15/C4 | D19: =D15/D4 | E19: =E15/E4 | F19: =F15/F4 | G19: =G15/G4
A20: Capex / revenue | C20: =C12/C4 | D20: =D12/D4 | E20: =E12/E4 | F20: =F12/F4 | G20: =G12/G4
A21: Net debt / EBITDA | C21: =Inputs!$B$12/C5 | D21: =Inputs!$B$12/D5 | E21: =Inputs!$B$12/E5 | F21: =Inputs!$B$12/F5 | G21: =Inputs!$B$12/G5

Sheet Valuation
A1: Valuation — DCF
A3: Discounted cash flow
C4: Y1 | D4: Y2 | E4: Y3 | F4: Y4 | G4: Y5
A5: FCFF | C5: =Forecast!C15 | D5: =Forecast!D15 | E5: =Forecast!E15 | F5: =Forecast!F15 | G5: =Forecast!G15
A6: Discount factor | C6: =1/(1+Inputs!$B$10)^1 | D6: =1/(1+Inputs!$B$10)^2 | E6: =1/(1+Inputs!$B$10)^3 | F6: =1/(1+Inputs!$B$10)^4 | G6: =1/(1+Inputs!$B$10)^5
A7: PV of FCFF | C7: =C5*C6 | D7: =D5*D6 | E7: =E5*E6 | F7: =F5*F6 | G7: =G5*G6
A9: Sum of PV of FCFF | B9: =SUM(C7:G7)
A10: Terminal value (Y5) | B10: =Forecast!G15*(1+Inputs!$B$11)/(Inputs!$B$10-Inputs!$B$11)
A11: PV of terminal value | B11: =B10/(1+Inputs!$B$10)^5
A12: Enterprise value | B12: =B9+B11
A13: Less: net debt | B13: =Inputs!$B$12
A14: Equity value | B14: =B12-B13
A15: Shares outstanding (m) | B15: =Inputs!$B$13
A16: Per-share value (USD) | B16: =B14*1000/B15
A17: Implied FY+1 EV/EBITDA | B17: =B12/Forecast!C5
